CHANGES.txt
ZopePublicLicense.txt
buildout.cfg
setup.py
van/__init__.py
van.testing.egg-info/PKG-INFO
van.testing.egg-info/SOURCES.txt
van.testing.egg-info/dependency_links.txt
van.testing.egg-info/namespace_packages.txt
van.testing.egg-info/not-zip-safe
van.testing.egg-info/requires.txt
van.testing.egg-info/top_level.txt
van/testing/README.txt
van/testing/__init__.py
van/testing/ftesting.zcml
van/testing/layer.py
van/testing/testbrowser.txt
van/testing/tests.py
van/testing/zcml_features.txt