Metadata-Version: 1.0
Name: van.testing
Version: 3.0.0
Summary: Layers for zope.testing to simplify test setups
Home-page: http://pypi.python.org/pypi/van.testing
Author: Vanguardistas LLC
Author-email: zope-dev@zope.org
License: ZPL 2.1
Platform: UNKNOWN
Classifier: Environment :: Web Environment
Classifier: Intended Audience :: Developers
Classifier: License :: OSI Approved :: Zope Public License
Classifier: Programming Language :: Python
Classifier: Topic :: Software Development :: Testing
Classifier: Development Status :: 5 - Production/Stable
